Workbook

Sheet Read Me
A1: Destination Pet: business case for a connected-care data platform
A2: Prepared as a portfolio exercise by Chris Lavelle, from public information only. Not affiliated with or reviewed by Destination Pet.
A4: The question
A5: What is a data and analytics platform worth to Destination Pet, given that it owns every location and therefore its own data?
A7: How ownership changes the case
A8: 1. No partner incentives: the largest variable cost in the partner-network version of this model disappears.
A9: 2. Most value is internal: staffing, cross-selling across Connected Care services, and clinical quality, which raise EBITDA directly and therefore exit value.
A10: 3. External data sales are possible but gated by scale; some products (rare drug-safety studies) need far more veterinary volume than one company has.
A11: 4. New costs appear instead: unifying systems across acquired brands, and consent and privacy work.
A13: How to use
A14: Edit blue cells on the Assumptions sheet. Peach cells are company facts to confirm with Destination Pet finance and operations. Yellow cells are the key levers.
A15: The Summary sheet shows all three scenarios; the Model sheet shows the year-by-year build.
... A18: Operating inputs (labor cost, customers and patients per location, prices, the number of veterinary locations) are ILLUSTRATIVE PLACEHOLDERS. Effect sizes from TailSignal come from simulated data and carry a realization haircut. Replace inputs with company data before any decision.

Sheet Summary
A1: Summary by scenario
A2: Placeholders drive these results; see Read Me.
A4: Measure | B4: Low | C4: Base | D4: High
A5: Internal value, Year 5 (EBITDA) | B5: =Model!F14 -> 2316400 | C5: =Model!F40 -> 4632800 | D5: =Model!F66 -> 6485920
A6: External data revenue, Year 5 | B6: =Model!F19 -> 768000 | C6: =Model!F45 -> 960000 | D6: =Model!F71 -> 1104000
A7: Platform cost, Year 5 | B7: =Model!F25 -> 2796000 | C7: =Model!F51 -> 2796000 | D7: =Model!F77 -> 2796000
A8: Net EBITDA impact, Year 5 | B8: =Model!F26 -> 288400 | C8: =Model!F52 -> 2796800 | D8: =Model!F78 -> 4793920
A9: Cumulative net impact, Years 1-5 | B9: =Model!F27 -> -3184600 | C9: =Model!F53 -> 5458800 | D9: =Model!F79 -> 12346720
A10: Enterprise value from Year-5 net impact (x exit multiple) | B10: =MAX(0,Model!F26)*Assumptions!$B$62 -> 3460800 | C10: =MAX(0,Model!F52)*Assumptions!$B$62 -> 33561600 | D10: =MAX(0,Model!F78)*Assumptions!$B$62 -> 57527040
A11: Payback year (cumulative impact turns positive) | B11: =IF(MIN(Model!B28:F28)=99,"Not within 5 years","Year "&MIN(Model!B28:F28)) -> Not within 5 years | C11: =IF(MIN(Model!B54:F54)=99,"Not within 5 years","Year "&MIN(Model!B54:F54)) -> Year 3 | D11: =IF(MIN(Model!B80:F80)=99,"Not within 5 years","Year "&MIN(Model!B80:F80)) -> Year 2
A13: Where Year-5 value comes from (Base) | B13: Amount ($) | C13: Share of gross value
A14: Staffing savings | B14: =Model!F36 -> 3920000 | C14: =IF(SUM($B$14:$B$21)=0,0,B14/SUM($B$14:$B$21)) -> 0.70090116
A15: Connected Care cross-sell | B15: =Model!F37 -> 460800 | C15: =IF(SUM($B$14:$B$21)=0,0,B15/SUM($B$14:$B$21)) -> 0.082391646
A16: Dental capture | B16: =Model!F38 -> 252000 | C16: =IF(SUM($B$14:$B$21)=0,0,B16/SUM($B$14:$B$21)) -> 0.045057932
A17: Membership retention | B17: =Model!F39 -> 0 | C17: =IF(SUM($B$14:$B$21)=0,0,B17/SUM($B$14:$B$21)) -> 0
A18: Data licenses | B18: =Model!F41 -> 720000 | C18: =IF(SUM($B$14:$B$21)=0,0,B18/SUM($B$14:$B$21)) -> 0.12873695
A19: Research reports | B19: =Model!F42 -> 240000 | C19: =IF(SUM($B$14:$B$21)=0,0,B19/SUM($B$14:$B$21)) -> 0.042912316
A20: Common side-effect studies | B20: =Model!F43 -> 0 | C20: =IF(SUM($B$14:$B$21)=0,0,B20/SUM($B$14:$B$21)) -> 0
A21: Rare side-effect studies | B21: =Model!F44 -> 0 | C21: =IF(SUM($B$14:$B$21)=0,0,B21/SUM($B$14:$B$21)) -> 0

Sheet Scale Gates
A1: What one owned network can and cannot unlock
A3: Capability | B3: Needs | C3: Year reached (Base) | D3: Base, Year 5 | F3: Implication
A4: Data licenses (pets observed per year) | B4: =Assumptions!$B$37 -> 100000 | C4: =IF(Model!B34>=$B4,"Year 1",IF(Model!C34>=$B4,"Year 2",IF(Model!D34>=$B4,"Year 3",IF(Model!E34>=$B4,"Year 4",IF(Model!F34>=$B4,"Year 5","Not in 5 years"))))) -> Year 2 | D4: =Model!F34 -> 480000 | F4: Reached early: owning every channel gives volume quickly
A5: Common side-effect studies (dog records, 4 yrs) | B5: =Assumptions!$B$40 -> 792000 | C5: =IF(Model!B35>=$B5,"Year 1",IF(Model!C35>=$B5,"Year 2",IF(Model!D35>=$B5,"Year 3",IF(Model!E35>=$B5,"Year 4",IF(Model!F35>=$B5,"Year 5","Not in 5 years"))))) -> Not in 5 years | D5: =Model!F35 -> 469000 | F5: Depends on veterinary volume, not resort volume
A6: Rare side-effect studies (dog records, 4 yrs) | B6: =Assumptions!$B$41 -> 1287000 | C6: =IF(Model!B35>=$B6,"Year 1",IF(Model!C35>=$B6,"Year 2",IF(Model!D35>=$B6,"Year 3",IF(Model!E35>=$B6,"Year 4",IF(Model!F35>=$B6,"Year 5","Not in 5 years"))))) -> Not in 5 years | D6: =Model!F35 -> 469000 | F6: Likely needs a research partner or consortium beyond one company

Sheet Company Facts
A1: Fact | B1: Value | C1: Source
A2: Services | B2: Boarding, daycare, grooming, training, veterinary care | C2: https://www.destinationpet.com/about-us/about/
A3: Operating model | B3: Connected Care across services; Yourgi pet app | C3: https://www.destinationpet.com/about-us/about/
A4: Locations | B4: 160+ in more than 31 states (June 2023) | C4: https://www.prnewswire.com/news-releases/destination-pet-strengthens-position-in-the-pet-care-industry-with-pet-palace-acquisition-301856956.html
A5: Acquisition example | B5: Pet Palace: 11 facilities, 500+ employees (June 2023) | C5: Same press release
A6: Owner | B6: LetterOne (acquired November 2019) | C6: https://www.cbinsights.com/company/destination-pet
A7: 2025 performance | B7: Return to full-year profitability; revenue ahead of plan; M&A accretive | C7: https://letterone.com/news-and-insights/2025-year-in-review-l1-health/
A8: Yourgi app | B8: Gross booking value growing >100% a year; became a two-sided marketplace in November 2025 | C8: Same LetterOne review
A9: Not public (confirm) | B9: Number of veterinary locations, revenue and labor cost per location, active pets | C9: Inputs on the Assumptions sheet are placeholders

Sheet Assumptions
A1: Assumptions
A2: Blue = input · peach fill = company fact to confirm · yellow fill = key lever
A4: Scenarios
A5: Scenario | B5: Value effects × | C5: External prices × | G5: Note
A6: Low | B6: 0.5 | C6: 0.8 | G6: Value effects scale every internal benefit; prices scale every external sale
A7: Base | B7: 1 | C7: 1
A8: High | B8: 1.4 | C8: 1.15
A10: Network (company facts to confirm)
A11: Locations (all service types) | B11: 160 | G11: Public: 160+ (June 2023 press release)
A12: Locations with a veterinary clinic | B12: 40 | G12: Not public; placeholder
A13: Unique pets served per location per year | B13: 3000 | G13: Not public; placeholder
A14: Dogs with veterinary records per vet clinic per year | B14: 3500 | G14: Not public; placeholder
A15: Daycare and boarding labor cost per location ($ per year) | B15: 700000 | G15: Not public; placeholder
A16: Share of resort customers not using a company vet | B16: 0.8 | G16: Not public; placeholder
A18: Rollout
A19: Item | B19: Year 1 | C19: Year 2 | D19: Year 3 | E19: Year 4 | F19: Year 5 | G19: Note
A20: Share of locations live on the platform | B20: 0.15 | C20: 0.5 | D20: 0.85 | E20: 1 | F20: 1 | G20: Systems from acquired brands unified over two to three years
A22: Internal value drivers (effects from TailSignal, with a realization haircut)
A23: Driver | B23: Value | G23: Evidence
A24: Daycare staffing cost reduction from demand forecasting | B24: 0.07 | G24: TailSignal backtest, simulated data: 7% lower staffing cost than the seasonal baseline (docs/analytics_results.md)
A25: Realization of simulated effects in practice | B25: 0.5 | G25: Haircut for moving from simulation to operations
A26: Extra conversion of resort customers to company vet care (points) | B26: 0.01 | G26: Assumption: targeted Connected Care offers from daycare, boarding and grooming records
A27: Annual veterinary revenue per new client ($) | B27: 600 | G27: Placeholder
A28: Contribution margin on added veterinary revenue | B28: 0.4 | G28: Placeholder
A29: Extra dental cleanings per vet clinic per year from better charting | B29: 40 | G29: TailSignal: under-charting clinics record 35-43% less dental disease; bring them to the median
A30: Average dental cleaning price ($) | B30: 700 | G30: Placeholder
A31: Contribution margin on dental cleanings | B31: 0.45 | G31: Placeholder
A32: Membership retention benefit per location ($ per year) | B32: 0 | G32: TailSignal reminder-targeting pilot was inconclusive; set to zero until a larger pilot proves it
A34: External data revenue (illustrative prices)
A35: Item | B35: Value | G35: Basis
A36: Data-license annual contract value ($) | B36: 120000 | G36: De-identified cohort, Pet Health Index, service benchmarks
A37: Pets observed per year needed before licensing | B37: 100000 | G37: Privacy: 8% of pets suppressed at ~12,700 pets; assume ~8x that for clean releases
A38: Research report average price ($) | B38: 40000 | G38: Pet food, dental-care and drug makers
A39: Signal-validation study price ($ per study) | B39: 250000 | G39: Drug-safety study for a manufacturer
A40: Dog records needed for common side-effect studies (4-year window) | B40: 792000 | G40: TailSignal Model A2: ~80x a 9,900-dog network
A41: Dog records needed for rare side-effect studies (4-year window) | B41: 1287000 | G41: TailSignal Model A2: ~130x a 9,900-dog network
A42: Study delivery cost (% of study revenue) | B42: 0.4 | G42: Clinical review and annotation
A44: Volume by year | B44: Year 1 | C44: Year 2 | D44: Year 3 | E44: Year 4 | F44: Year 5 | G44: Note
A45: Data licensees | B45: 0 | C45: 2 | D45: 3 | E45: 5 | F45: 6 | G45: Sold only once the license gate is met
A46: Research reports sold | B46: 1 | C46: 3 | D46: 4 | E46: 5 | F46: 6
A47: Common side-effect studies (if gate met) | B47: 0 | C47: 0 | D47: 1 | E47: 2 | F47: 2
A48: Rare side-effect studies (if gate met) | B48: 0 | C48: 0 | D48: 0 | E48: 1 | F48: 1
A50: Costs
A51: Item | B51: Value | G51: Basis
A52: Loaded cost per data-team employee ($ per year) | B52: 200000 | G52: Placeholder
A53: System integration cost per location (one-time, $) | B53: 15000 | G53: Unify practice-management and booking systems from acquired brands
A54: Cloud and tooling, fixed ($ per year) | B54: 150000 | G54: Placeholder
A55: Cloud and tooling per live location ($ per year) | B55: 600 | G55: Placeholder
A56: Privacy, consent and legal ($ per year) | B56: 150000 | G56: Customer consent for de-identified use; data-sale contracts
A58: Headcount by year | B58: Year 1 | C58: Year 2 | D58: Year 3 | E58: Year 4 | F58: Year 5 | G58: Note
A59: Data team headcount | B59: 5 | C59: 8 | D59: 10 | E59: 11 | F59: 12 | G59: Data science, data engineering, analytics product, privacy
A61: Valuation
A62: EV / EBITDA exit multiple applied to run-rate uplift | B62: 12 | G62: Placeholder for a PE-owned multi-site pet services business; confirm with the deal team

Sheet Model
A1: Five-year build by scenario ($)
A2: All cells are formulas driven by the Assumptions sheet.
A4: Low scenario
A5: Line | B5: Year 1 | C5: Year 2 | D5: Year 3 | E5: Year 4 | F5: Year 5
A6: Live locations | B6: =ROUND(Assumptions!$B$11*Assumptions!B$20,0) -> 24 | C6: =ROUND(Assumptions!$B$11*Assumptions!C$20,0) -> 80 | D6: =ROUND(Assumptions!$B$11*Assumptions!D$20,0) -> 136 | E6: =ROUND(Assumptions!$B$11*Assumptions!E$20,0) -> 160 | F6: =ROUND(Assumptions!$B$11*Assumptions!F$20,0) -> 160
A7: Live vet clinics | B7: =ROUND(Assumptions!$B$12*Assumptions!B$20,0) -> 6 | C7: =ROUND(Assumptions!$B$12*Assumptions!C$20,0) -> 20 | D7: =ROUND(Assumptions!$B$12*Assumptions!D$20,0) -> 34 | E7: =ROUND(Assumptions!$B$12*Assumptions!E$20,0) -> 40 | F7: =ROUND(Assumptions!$B$12*Assumptions!F$20,0) -> 40
A8: Pets observed per year | B8: =B6*Assumptions!$B$13 -> 72000 | C8: =C6*Assumptions!$B$13 -> 240000 | D8: =D6*Assumptions!$B$13 -> 408000 | E8: =E6*Assumptions!$B$13 -> 480000 | F8: =F6*Assumptions!$B$13 -> 480000
A9: Dog veterinary records, trailing 4 years (study window) | B9: =SUM(B7:B7)*Assumptions!$B$14 -> 21000 | C9: =SUM(B7:C7)*Assumptions!$B$14 -> 91000 | D9: =SUM(B7:D7)*Assumptions!$B$14 -> 210000 | E9: =SUM(B7:E7)*Assumptions!$B$14 -> 350000 | F9: =SUM(C7:F7)*Assumptions!$B$14 -> 469000
A10: Internal: daycare and boarding staffing savings | B10: =B6*Assumptions!$B$15*Assumptions!$B$24*Assumptions!$B$25*Assumptions!$B$6 -> 294000 | C10: =C6*Assumptions!$B$15*Assumptions!$B$24*Assumptions!$B$25*Assumptions!$B$6 -> 980000 | D10: =D6*Assumptions!$B$15*Assumptions!$B$24*Assumptions!$B$25*Assumptions!$B$6 -> 1666000 | E10: =E6*Assumptions!$B$15*Assumptions!$B$24*Assumptions!$B$25*Assumptions!$B$6 -> 1960000 | F10: =F6*Assumptions!$B$15*Assumptions!$B$24*Assumptions!$B$25*Assumptions!$B$6 -> 1960000
A11: Internal: Connected Care cross-sell to vet (contribution) | B11: =B6*Assumptions!$B$13*Assumptions!$B$16*Assumptions!$B$26*Assumptions!$B$27*Assumptions!$B$28*Assumptions!$B$25*Assumptions!$B$6 -> 34560 | C11: =C6*Assumptions!$B$13*Assumptions!$B$16*Assumptions!$B$26*Assumptions!$B$27*Assumptions!$B$28*Assumptions!$B$25*Assumptions!$B$6 -> 115200 | D11: =D6*Assumptions!$B$13*Assumptions!$B$16*Assumptions!$B$26*Assumptions!$B$27*Assumptions!$B$28*Assumptions!$B$25*Assumptions!$B$6 -> 195840 | E11: =E6*Assumptions!$B$13*Assumptions!$B$16*Assumptions!$B$26*Assumptions!$B$27*Assumptions!$B$28*Assumptions!$B$25*Assumptions!$B$6 -> 230400 | F11: =F6*Assumptions!$B$13*Assumptions!$B$16*Assumptions!$B$26*Assumptions!$B$27*Assumptions!$B$28*Assumptions!$B$25*Assumptions!$B$6 -> 230400
A12: Internal: dental capture (contribution) | B12: =B7*Assumptions!$B$29*Assumptions!$B$30*Assumptions!$B$31*Assumptions!$B$25*Assumptions!$B$6 -> 18900 | C12: =C7*Assumptions!$B$29*Assumptions!$B$30*Assumptions!$B$31*Assumptions!$B$25*Assumptions!$B$6 -> 63000 | D12: =D7*Assumptions!$B$29*Assumptions!$B$30*Assumptions!$B$31*Assumptions!$B$25*Assumptions!$B$6 -> 107100 | E12: =E7*Assumptions!$B$29*Assumptions!$B$30*Assumptions!$B$31*Assumptions!$B$25*Assumptions!$B$6 -> 126000 | F12: =F7*Assumptions!$B$29*Assumptions!$B$30*Assumptions!$B$31*Assumptions!$B$25*Assumptions!$B$6 -> 126000
A13: Internal: membership retention | B13: =B6*Assumptions!$B$32*Assumptions!$B$6 -> 0 | C13: =C6*Assumptions!$B$32*Assumptions!$B$6 -> 0 | D13: =D6*Assumptions!$B$32*Assumptions!$B$6 -> 0 | E13: =E6*Assumptions!$B$32*Assumptions!$B$6 -> 0 | F13: =F6*Assumptions!$B$32*Assumptions!$B$6 -> 0
A14: Internal value (EBITDA) | B14: =SUM(B10:B13) -> 347460 | C14: =SUM(C10:C13) -> 1158200 | D14: =SUM(D10:D13) -> 1968940 | E14: =SUM(E10:E13) -> 2316400 | F14: =SUM(F10:F13) -> 2316400
A15: External: data licenses | B15: =IF(B8>=Assumptions!$B$37,Assumptions!B$45*Assumptions!$B$36*Assumptions!$C$6,0) -> 0 | C15: =IF(C8>=Assumptions!$B$37,Assumptions!C$45*Assumptions!$B$36*Assumptions!$C$6,0) -> 192000 | D15: =IF(D8>=Assumptions!$B$37,Assumptions!D$45*Assumptions!$B$36*Assumptions!$C$6,0) -> 288000 | E15: =IF(E8>=Assumptions!$B$37,Assumptions!E$45*Assumptions!$B$36*Assumptions!$C$6,0) -> 480000 | F15: =IF(F8>=Assumptions!$B$37,Assumptions!F$45*Assumptions!$B$36*Assumptions!$C$6,0) -> 576000
A16: External: research reports | B16: =Assumptions!B$46*Assumptions!$B$38*Assumptions!$C$6 -> 32000 | C16: =Assumptions!C$46*Assumptions!$B$38*Assumptions!$C$6 -> 96000 | D16: =Assumptions!D$46*Assumptions!$B$38*Assumptions!$C$6 -> 128000 | E16: =Assumptions!E$46*Assumptions!$B$38*Assumptions!$C$6 -> 160000 | F16: =Assumptions!F$46*Assumptions!$B$38*Assumptions!$C$6 -> 192000
A17: External: common side-effect studies | B17: =IF(B9>=Assumptions!$B$40,Assumptions!B$47*Assumptions!$B$39*Assumptions!$C$6,0) -> 0 | C17: =IF(C9>=Assumptions!$B$40,Assumptions!C$47*Assumptions!$B$39*Assumptions!$C$6,0) -> 0 | D17: =IF(D9>=Assumptions!$B$40,Assumptions!D$47*Assumptions!$B$39*Assumptions!$C$6,0) -> 0 | E17: =IF(E9>=Assumptions!$B$40,Assumptions!E$47*Assumptions!$B$39*Assumptions!$C$6,0) -> 0 | F17: =IF(F9>=Assumptions!$B$40,Assumptions!F$47*Assumptions!$B$39*Assumptions!$C$6,0) -> 0
A18: External: rare side-effect studies | B18: =IF(B9>=Assumptions!$B$41,Assumptions!B$48*Assumptions!$B$39*Assumptions!$C$6,0) -> 0 | C18: =IF(C9>=Assumptions!$B$41,Assumptions!C$48*Assumptions!$B$39*Assumptions!$C$6,0) -> 0 | D18: =IF(D9>=Assumptions!$B$41,Assumptions!D$48*Assumptions!$B$39*Assumptions!$C$6,0) -> 0 | E18: =IF(E9>=Assumptions!$B$41,Assumptions!E$48*Assumptions!$B$39*Assumptions!$C$6,0) -> 0 | F18: =IF(F9>=Assumptions!$B$41,Assumptions!F$48*Assumptions!$B$39*Assumptions!$C$6,0) -> 0
A19: External revenue | B19: =SUM(B15:B18) -> 32000 | C19: =SUM(C15:C18) -> 288000 | D19: =SUM(D15:D18) -> 416000 | E19: =SUM(E15:E18) -> 640000 | F19: =SUM(F15:F18) -> 768000
A20: Data team | B20: =Assumptions!B$59*Assumptions!$B$52 -> 1000000 | C20: =Assumptions!C$59*Assumptions!$B$52 -> 1600000 | D20: =Assumptions!D$59*Assumptions!$B$52 -> 2000000 | E20: =Assumptions!E$59*Assumptions!$B$52 -> 2200000 | F20: =Assumptions!F$59*Assumptions!$B$52 -> 2400000
A21: System integration (one-time, newly live locations) | B21: =B6*Assumptions!$B$53 -> 360000 | C21: =MAX(0,C6-B6)*Assumptions!$B$53 -> 840000 | D21: =MAX(0,D6-C6)*Assumptions!$B$53 -> 840000 | E21: =MAX(0,E6-D6)*Assumptions!$B$53 -> 360000 | F21: =MAX(0,F6-E6)*Assumptions!$B$53 -> 0
A22: Cloud and tooling | B22: =Assumptions!$B$54+B6*Assumptions!$B$55 -> 164400 | C22: =Assumptions!$B$54+C6*Assumptions!$B$55 -> 198000 | D22: =Assumptions!$B$54+D6*Assumptions!$B$55 -> 231600 | E22: =Assumptions!$B$54+E6*Assumptions!$B$55 -> 246000 | F22: =Assumptions!$B$54+F6*Assumptions!$B$55 -> 246000
A23: Privacy, consent and legal | B23: =Assumptions!$B$56 -> 150000 | C23: =Assumptions!$B$56 -> 150000 | D23: =Assumptions!$B$56 -> 150000 | E23: =Assumptions!$B$56 -> 150000 | F23: =Assumptions!$B$56 -> 150000
A24: Study delivery | B24: =(B17+B18)*Assumptions!$B$42 -> 0 | C24: =(C17+C18)*Assumptions!$B$42 -> 0 | D24: =(D17+D18)*Assumptions!$B$42 -> 0 | E24: =(E17+E18)*Assumptions!$B$42 -> 0 | F24: =(F17+F18)*Assumptions!$B$42 -> 0
A25: Total platform cost | B25: =SUM(B20:B24) -> 1674400 | C25: =SUM(C20:C24) -> 2788000 | D25: =SUM(D20:D24) -> 3221600 | E25: =SUM(E20:E24) -> 2956000 | F25: =SUM(F20:F24) -> 2796000
A26: Net EBITDA impact | B26: =B14+B19-B25 -> -1294940 | C26: =C14+C19-C25 -> -1341800 | D26: =D14+D19-D25 -> -836660 | E26: =E14+E19-E25 -> 400 | F26: =F14+F19-F25 -> 288400
A27: Cumulative net impact | B27: =B26 -> -1294940 | C27: =B27+C26 -> -2636740 | D27: =C27+D26 -> -3473400 | E27: =D27+E26 -> -3473000 | F27: =E27+F26 -> -3184600
A28: Helper: year number if cumulative impact positive (else 99) | B28: =IF(B27>0,1,99) -> 99 | C28: =IF(C27>0,2,99) -> 99 | D28: =IF(D27>0,3,99) -> 99 | E28: =IF(E27>0,4,99) -> 99 | F28: =IF(F27>0,5,99) -> 99
A30: Base scenario
A31: Line | B31: Year 1 | C31: Year 2 | D31: Year 3 | E31: Year 4 | F31: Year 5
A32: Live locations | B32: =ROUND(Assumptions!$B$11*Assumptions!B$20,0) -> 24 | C32: =ROUND(Assumptions!$B$11*Assumptions!C$20,0) -> 80 | D32: =ROUND(Assumptions!$B$11*Assumptions!D$20,0) -> 136 | E32: =ROUND(Assumptions!$B$11*Assumptions!E$20,0) -> 160 | F32: =ROUND(Assumptions!$B$11*Assumptions!F$20,0) -> 160
A33: Live vet clinics | B33: =ROUND(Assumptions!$B$12*Assumptions!B$20,0) -> 6 | C33: =ROUND(Assumptions!$B$12*Assumptions!C$20,0) -> 20 | D33: =ROUND(Assumptions!$B$12*Assumptions!D$20,0) -> 34 | E33: =ROUND(Assumptions!$B$12*Assumptions!E$20,0) -> 40 | F33: =ROUND(Assumptions!$B$12*Assumptions!F$20,0) -> 40
A34: Pets observed per year | B34: =B32*Assumptions!$B$13 -> 72000 | C34: =C32*Assumptions!$B$13 -> 240000 | D34: =D32*Assumptions!$B$13 -> 408000 | E34: =E32*Assumptions!$B$13 -> 480000 | F34: =F32*Assumptions!$B$13 -> 480000
A35: Dog veterinary records, trailing 4 years (study window) | B35: =SUM(B33:B33)*Assumptions!$B$14 -> 21000 | C35: =SUM(B33:C33)*Assumptions!$B$14 -> 91000 | D35: =SUM(B33:D33)*Assumptions!$B$14 -> 210000 | E35: =SUM(B33:E33)*Assumptions!$B$14 -> 350000 | F35: =SUM(C33:F33)*Assumptions!$B$14 -> 469000
A36: Internal: daycare and boarding staffing savings | B36: =B32*Assumptions!$B$15*Assumptions!$B$24*Assumptions!$B$25*Assumptions!$B$7 -> 588000 | C36: =C32*Assumptions!$B$15*Assumptions!$B$24*Assumptions!$B$25*Assumptions!$B$7 -> 1960000 | D36: =D32*Assumptions!$B$15*Assumptions!$B$24*Assumptions!$B$25*Assumptions!$B$7 -> 3332000 | E36: =E32*Assumptions!$B$15*Assumptions!$B$24*Assumptions!$B$25*Assumptions!$B$7 -> 3920000 | F36: =F32*Assumptions!$B$15*Assumptions!$B$24*Assumptions!$B$25*Assumptions!$B$7 -> 3920000
A37: Internal: Connected Care cross-sell to vet (contribution) | B37: =B32*Assumptions!$B$13*Assumptions!$B$16*Assumptions!$B$26*Assumptions!$B$27*Assumptions!$B$28*Assumptions!$B$25*Assumptions!$B$7 -> 69120 | C37: =C32*Assumptions!$B$13*Assumptions!$B$16*Assumptions!$B$26*Assumptions!$B$27*Assumptions!$B$28*Assumptions!$B$25*Assumptions!$B$7 -> 230400 | D37: =D32*Assumptions!$B$13*Assumptions!$B$16*Assumptions!$B$26*Assumptions!$B$27*Assumptions!$B$28*Assumptions!$B$25*Assumptions!$B$7 -> 391680 | E37: =E32*Assumptions!$B$13*Assumptions!$B$16*Assumptions!$B$26*Assumptions!$B$27*Assumptions!$B$28*Assumptions!$B$25*Assumptions!$B$7 -> 460800 | F37: =F32*Assumptions!$B$13*Assumptions!$B$16*Assumptions!$B$26*Assumptions!$B$27*Assumptions!$B$28*Assumptions!$B$25*Assumptions!$B$7 -> 460800
A38: Internal: dental capture (contribution) | B38: =B33*Assumptions!$B$29*Assumptions!$B$30*Assumptions!$B$31*Assumptions!$B$25*Assumptions!$B$7 -> 37800 | C38: =C33*Assumptions!$B$29*Assumptions!$B$30*Assumptions!$B$31*Assumptions!$B$25*Assumptions!$B$7 -> 126000 | D38: =D33*Assumptions!$B$29*Assumptions!$B$30*Assumptions!$B$31*Assumptions!$B$25*Assumptions!$B$7 -> 214200 | E38: =E33*Assumptions!$B$29*Assumptions!$B$30*Assumptions!$B$31*Assumptions!$B$25*Assumptions!$B$7 -> 252000 | F38: =F33*Assumptions!$B$29*Assumptions!$B$30*Assumptions!$B$31*Assumptions!$B$25*Assumptions!$B$7 -> 252000
A39: Internal: membership retention | B39: =B32*Assumptions!$B$32*Assumptions!$B$7 -> 0 | C39: =C32*Assumptions!$B$32*Assumptions!$B$7 -> 0 | D39: =D32*Assumptions!$B$32*Assumptions!$B$7 -> 0 | E39: =E32*Assumptions!$B$32*Assumptions!$B$7 -> 0 | F39: =F32*Assumptions!$B$32*Assumptions!$B$7 -> 0
A40: Internal value (EBITDA) | B40: =SUM(B36:B39) -> 694920 | C40: =SUM(C36:C39) -> 2316400 | D40: =SUM(D36:D39) -> 3937880 | E40: =SUM(E36:E39) -> 4632800 | F40: =SUM(F36:F39) -> 4632800
A41: External: data licenses | B41: =IF(B34>=Assumptions!$B$37,Assumptions!B$45*Assumptions!$B$36*Assumptions!$C$7,0) -> 0 | C41: =IF(C34>=Assumptions!$B$37,Assumptions!C$45*Assumptions!$B$36*Assumptions!$C$7,0) -> 240000 | D41: =IF(D34>=Assumptions!$B$37,Assumptions!D$45*Assumptions!$B$36*Assumptions!$C$7,0) -> 360000 | E41: =IF(E34>=Assumptions!$B$37,Assumptions!E$45*Assumptions!$B$36*Assumptions!$C$7,0) -> 600000 | F41: =IF(F34>=Assumptions!$B$37,Assumptions!F$45*Assumptions!$B$36*Assumptions!$C$7,0) -> 720000
A42: External: research reports | B42: =Assumptions!B$46*Assumptions!$B$38*Assumptions!$C$7 -> 40000 | C42: =Assumptions!C$46*Assumptions!$B$38*Assumptions!$C$7 -> 120000 | D42: =Assumptions!D$46*Assumptions!$B$38*Assumptions!$C$7 -> 160000 | E42: =Assumptions!E$46*Assumptions!$B$38*Assumptions!$C$7 -> 200000 | F42: =Assumptions!F$46*Assumptions!$B$38*Assumptions!$C$7 -> 240000
A43: External: common side-effect studies | B43: =IF(B35>=Assumptions!$B$40,Assumptions!B$47*Assumptions!$B$39*Assumptions!$C$7,0) -> 0 | C43: =IF(C35>=Assumptions!$B$40,Assumptions!C$47*Assumptions!$B$39*Assumptions!$C$7,0) -> 0 | D43: =IF(D35>=Assumptions!$B$40,Assumptions!D$47*Assumptions!$B$39*Assumptions!$C$7,0) -> 0 | E43: =IF(E35>=Assumptions!$B$40,Assumptions!E$47*Assumptions!$B$39*Assumptions!$C$7,0) -> 0 | F43: =IF(F35>=Assumptions!$B$40,Assumptions!F$47*Assumptions!$B$39*Assumptions!$C$7,0) -> 0
A44: External: rare side-effect studies | B44: =IF(B35>=Assumptions!$B$41,Assumptions!B$48*Assumptions!$B$39*Assumptions!$C$7,0) -> 0 | C44: =IF(C35>=Assumptions!$B$41,Assumptions!C$48*Assumptions!$B$39*Assumptions!$C$7,0) -> 0 | D44: =IF(D35>=Assumptions!$B$41,Assumptions!D$48*Assumptions!$B$39*Assumptions!$C$7,0) -> 0 | E44: =IF(E35>=Assumptions!$B$41,Assumptions!E$48*Assumptions!$B$39*Assumptions!$C$7,0) -> 0 | F44: =IF(F35>=Assumptions!$B$41,Assumptions!F$48*Assumptions!$B$39*Assumptions!$C$7,0) -> 0
A45: External revenue | B45: =SUM(B41:B44) -> 40000 | C45: =SUM(C41:C44) -> 360000 | D45: =SUM(D41:D44) -> 520000 | E45: =SUM(E41:E44) -> 800000 | F45: =SUM(F41:F44) -> 960000
A46: Data team | B46: =Assumptions!B$59*Assumptions!$B$52 -> 1000000 | C46: =Assumptions!C$59*Assumptions!$B$52 -> 1600000 | D46: =Assumptions!D$59*Assumptions!$B$52 -> 2000000 | E46: =Assumptions!E$59*Assumptions!$B$52 -> 2200000 | F46: =Assumptions!F$59*Assumptions!$B$52 -> 2400000
A47: System integration (one-time, newly live locations) | B47: =B32*Assumptions!$B$53 -> 360000 | C47: =MAX(0,C32-B32)*Assumptions!$B$53 -> 840000 | D47: =MAX(0,D32-C32)*Assumptions!$B$53 -> 840000 | E47: =MAX(0,E32-D32)*Assumptions!$B$53 -> 360000 | F47: =MAX(0,F32-E32)*Assumptions!$B$53 -> 0
A48: Cloud and tooling | B48: =Assumptions!$B$54+B32*Assumptions!$B$55 -> 164400 | C48: =Assumptions!$B$54+C32*Assumptions!$B$55 -> 198000 | D48: =Assumptions!$B$54+D32*Assumptions!$B$55 -> 231600 | E48: =Assumptions!$B$54+E32*Assumptions!$B$55 -> 246000 | F48: =Assumptions!$B$54+F32*Assumptions!$B$55 -> 246000
A49: Privacy, consent and legal | B49: =Assumptions!$B$56 -> 150000 | C49: =Assumptions!$B$56 -> 150000 | D49: =Assumptions!$B$56 -> 150000 | E49: =Assumptions!$B$56 -> 150000 | F49: =Assumptions!$B$56 -> 150000
A50: Study delivery | B50: =(B43+B44)*Assumptions!$B$42 -> 0 | C50: =(C43+C44)*Assumptions!$B$42 -> 0 | D50: =(D43+D44)*Assumptions!$B$42 -> 0 | E50: =(E43+E44)*Assumptions!$B$42 -> 0 | F50: =(F43+F44)*Assumptions!$B$42 -> 0
A51: Total platform cost | B51: =SUM(B46:B50) -> 1674400 | C51: =SUM(C46:C50) -> 2788000 | D51: =SUM(D46:D50) -> 3221600 | E51: =SUM(E46:E50) -> 2956000 | F51: =SUM(F46:F50) -> 2796000
A52: Net EBITDA impact | B52: =B40+B45-B51 -> -939480 | C52: =C40+C45-C51 -> -111600 | D52: =D40+D45-D51 -> 1236280 | E52: =E40+E45-E51 -> 2476800 | F52: =F40+F45-F51 -> 2796800
A53: Cumulative net impact | B53: =B52 -> -939480 | C53: =B53+C52 -> -1051080 | D53: =C53+D52 -> 185200 | E53: =D53+E52 -> 2662000 | F53: =E53+F52 -> 5458800
A54: Helper: year number if cumulative impact positive (else 99) | B54: =IF(B53>0,1,99) -> 99 | C54: =IF(C53>0,2,99) -> 99 | D54: =IF(D53>0,3,99) -> 3 | E54: =IF(E53>0,4,99) -> 4 | F54: =IF(F53>0,5,99) -> 5
A56: High scenario
A57: Line | B57: Year 1 | C57: Year 2 | D57: Year 3 | E57: Year 4 | F57: Year 5
A58: Live locations | B58: =ROUND(Assumptions!$B$11*Assumptions!B$20,0) -> 24 | C58: =ROUND(Assumptions!$B$11*Assumptions!C$20,0) -> 80 | D58: =ROUND(Assumptions!$B$11*Assumptions!D$20,0) -> 136 | E58: =ROUND(Assumptions!$B$11*Assumptions!E$20,0) -> 160 | F58: =ROUND(Assumptions!$B$11*Assumptions!F$20,0) -> 160
A59: Live vet clinics | B59: =ROUND(Assumptions!$B$12*Assumptions!B$20,0) -> 6 | C59: =ROUND(Assumptions!$B$12*Assumptions!C$20,0) -> 20 | D59: =ROUND(Assumptions!$B$12*Assumptions!D$20,0) -> 34 | E59: =ROUND(Assumptions!$B$12*Assumptions!E$20,0) -> 40 | F59: =ROUND(Assumptions!$B$12*Assumptions!F$20,0) -> 40
A60: Pets observed per year | B60: =B58*Assumptions!$B$13 -> 72000 | C60: =C58*Assumptions!$B$13 -> 240000 | D60: =D58*Assumptions!$B$13 -> 408000 | E60: =E58*Assumptions!$B$13 -> 480000 | F60: =F58*Assumptions!$B$13 -> 480000
A61: Dog veterinary records, trailing 4 years (study window) | B61: =SUM(B59:B59)*Assumptions!$B$14 -> 21000 | C61: =SUM(B59:C59)*Assumptions!$B$14 -> 91000 | D61: =SUM(B59:D59)*Assumptions!$B$14 -> 210000 | E61: =SUM(B59:E59)*Assumptions!$B$14 -> 350000 | F61: =SUM(C59:F59)*Assumptions!$B$14 -> 469000
A62: Internal: daycare and boarding staffing savings | B62: =B58*Assumptions!$B$15*Assumptions!$B$24*Assumptions!$B$25*Assumptions!$B$8 -> 823200 | C62: =C58*Assumptions!$B$15*Assumptions!$B$24*Assumptions!$B$25*Assumptions!$B$8 -> 2744000 | D62: =D58*Assumptions!$B$15*Assumptions!$B$24*Assumptions!$B$25*Assumptions!$B$8 -> 4664800 | E62: =E58*Assumptions!$B$15*Assumptions!$B$24*Assumptions!$B$25*Assumptions!$B$8 -> 5488000 | F62: =F58*Assumptions!$B$15*Assumptions!$B$24*Assumptions!$B$25*Assumptions!$B$8 -> 5488000
A63: Internal: Connected Care cross-sell to vet (contribution) | B63: =B58*Assumptions!$B$13*Assumptions!$B$16*Assumptions!$B$26*Assumptions!$B$27*Assumptions!$B$28*Assumptions!$B$25*Assumptions!$B$8 -> 96768 | C63: =C58*Assumptions!$B$13*Assumptions!$B$16*Assumptions!$B$26*Assumptions!$B$27*Assumptions!$B$28*Assumptions!$B$25*Assumptions!$B$8 -> 322560 | D63: =D58*Assumptions!$B$13*Assumptions!$B$16*Assumptions!$B$26*Assumptions!$B$27*Assumptions!$B$28*Assumptions!$B$25*Assumptions!$B$8 -> 548352 | E63: =E58*Assumptions!$B$13*Assumptions!$B$16*Assumptions!$B$26*Assumptions!$B$27*Assumptions!$B$28*Assumptions!$B$25*Assumptions!$B$8 -> 645120 | F63: =F58*Assumptions!$B$13*Assumptions!$B$16*Assumptions!$B$26*Assumptions!$B$27*Assumptions!$B$28*Assumptions!$B$25*Assumptions!$B$8 -> 645120
A64: Internal: dental capture (contribution) | B64: =B59*Assumptions!$B$29*Assumptions!$B$30*Assumptions!$B$31*Assumptions!$B$25*Assumptions!$B$8 -> 52920 | C64: =C59*Assumptions!$B$29*Assumptions!$B$30*Assumptions!$B$31*Assumptions!$B$25*Assumptions!$B$8 -> 176400 | D64: =D59*Assumptions!$B$29*Assumptions!$B$30*Assumptions!$B$31*Assumptions!$B$25*Assumptions!$B$8 -> 299880 | E64: =E59*Assumptions!$B$29*Assumptions!$B$30*Assumptions!$B$31*Assumptions!$B$25*Assumptions!$B$8 -> 352800 | F64: =F59*Assumptions!$B$29*Assumptions!$B$30*Assumptions!$B$31*Assumptions!$B$25*Assumptions!$B$8 -> 352800
A65: Internal: membership retention | B65: =B58*Assumptions!$B$32*Assumptions!$B$8 -> 0 | C65: =C58*Assumptions!$B$32*Assumptions!$B$8 -> 0 | D65: =D58*Assumptions!$B$32*Assumptions!$B$8 -> 0 | E65: =E58*Assumptions!$B$32*Assumptions!$B$8 -> 0 | F65: =F58*Assumptions!$B$32*Assumptions!$B$8 -> 0
A66: Internal value (EBITDA) | B66: =SUM(B62:B65) -> 972888 | C66: =SUM(C62:C65) -> 3242960 | D66: =SUM(D62:D65) -> 5513032 | E66: =SUM(E62:E65) -> 6485920 | F66: =SUM(F62:F65) -> 6485920
A67: External: data licenses | B67: =IF(B60>=Assumptions!$B$37,Assumptions!B$45*Assumptions!$B$36*Assumptions!$C$8,0) -> 0 | C67: =IF(C60>=Assumptions!$B$37,Assumptions!C$45*Assumptions!$B$36*Assumptions!$C$8,0) -> 276000 | D67: =IF(D60>=Assumptions!$B$37,Assumptions!D$45*Assumptions!$B$36*Assumptions!$C$8,0) -> 414000 | E67: =IF(E60>=Assumptions!$B$37,Assumptions!E$45*Assumptions!$B$36*Assumptions!$C$8,0) -> 690000 | F67: =IF(F60>=Assumptions!$B$37,Assumptions!F$45*Assumptions!$B$36*Assumptions!$C$8,0) -> 828000
A68: External: research reports | B68: =Assumptions!B$46*Assumptions!$B$38*Assumptions!$C$8 -> 46000 | C68: =Assumptions!C$46*Assumptions!$B$38*Assumptions!$C$8 -> 138000 | D68: =Assumptions!D$46*Assumptions!$B$38*Assumptions!$C$8 -> 184000 | E68: =Assumptions!E$46*Assumptions!$B$38*Assumptions!$C$8 -> 230000 | F68: =Assumptions!F$46*Assumptions!$B$38*Assumptions!$C$8 -> 276000
A69: External: common side-effect studies | B69: =IF(B61>=Assumptions!$B$40,Assumptions!B$47*Assumptions!$B$39*Assumptions!$C$8,0) -> 0 | C69: =IF(C61>=Assumptions!$B$40,Assumptions!C$47*Assumptions!$B$39*Assumptions!$C$8,0) -> 0 | D69: =IF(D61>=Assumptions!$B$40,Assumptions!D$47*Assumptions!$B$39*Assumptions!$C$8,0) -> 0 | E69: =IF(E61>=Assumptions!$B$40,Assumptions!E$47*Assumptions!$B$39*Assumptions!$C$8,0) -> 0 | F69: =IF(F61>=Assumptions!$B$40,Assumptions!F$47*Assumptions!$B$39*Assumptions!$C$8,0) -> 0
A70: External: rare side-effect studies | B70: =IF(B61>=Assumptions!$B$41,Assumptions!B$48*Assumptions!$B$39*Assumptions!$C$8,0) -> 0 | C70: =IF(C61>=Assumptions!$B$41,Assumptions!C$48*Assumptions!$B$39*Assumptions!$C$8,0) -> 0 | D70: =IF(D61>=Assumptions!$B$41,Assumptions!D$48*Assumptions!$B$39*Assumptions!$C$8,0) -> 0 | E70: =IF(E61>=Assumptions!$B$41,Assumptions!E$48*Assumptions!$B$39*Assumptions!$C$8,0) -> 0 | F70: =IF(F61>=Assumptions!$B$41,Assumptions!F$48*Assumptions!$B$39*Assumptions!$C$8,0) -> 0
A71: External revenue | B71: =SUM(B67:B70) -> 46000 | C71: =SUM(C67:C70) -> 414000 | D71: =SUM(D67:D70) -> 598000 | E71: =SUM(E67:E70) -> 920000 | F71: =SUM(F67:F70) -> 1104000
A72: Data team | B72: =Assumptions!B$59*Assumptions!$B$52 -> 1000000 | C72: =Assumptions!C$59*Assumptions!$B$52 -> 1600000 | D72: =Assumptions!D$59*Assumptions!$B$52 -> 2000000 | E72: =Assumptions!E$59*Assumptions!$B$52 -> 2200000 | F72: =Assumptions!F$59*Assumptions!$B$52 -> 2400000
A73: System integration (one-time, newly live locations) | B73: =B58*Assumptions!$B$53 -> 360000 | C73: =MAX(0,C58-B58)*Assumptions!$B$53 -> 840000 | D73: =MAX(0,D58-C58)*Assumptions!$B$53 -> 840000 | E73: =MAX(0,E58-D58)*Assumptions!$B$53 -> 360000 | F73: =MAX(0,F58-E58)*Assumptions!$B$53 -> 0
A74: Cloud and tooling | B74: =Assumptions!$B$54+B58*Assumptions!$B$55 -> 164400 | C74: =Assumptions!$B$54+C58*Assumptions!$B$55 -> 198000 | D74: =Assumptions!$B$54+D58*Assumptions!$B$55 -> 231600 | E74: =Assumptions!$B$54+E58*Assumptions!$B$55 -> 246000 | F74: =Assumptions!$B$54+F58*Assumptions!$B$55 -> 246000
A75: Privacy, consent and legal | B75: =Assumptions!$B$56 -> 150000 | C75: =Assumptions!$B$56 -> 150000 | D75: =Assumptions!$B$56 -> 150000 | E75: =Assumptions!$B$56 -> 150000 | F75: =Assumptions!$B$56 -> 150000
A76: Study delivery | B76: =(B69+B70)*Assumptions!$B$42 -> 0 | C76: =(C69+C70)*Assumptions!$B$42 -> 0 | D76: =(D69+D70)*Assumptions!$B$42 -> 0 | E76: =(E69+E70)*Assumptions!$B$42 -> 0 | F76: =(F69+F70)*Assumptions!$B$42 -> 0
A77: Total platform cost | B77: =SUM(B72:B76) -> 1674400 | C77: =SUM(C72:C76) -> 2788000 | D77: =SUM(D72:D76) -> 3221600 | E77: =SUM(E72:E76) -> 2956000 | F77: =SUM(F72:F76) -> 2796000
A78: Net EBITDA impact | B78: =B66+B71-B77 -> -655512 | C78: =C66+C71-C77 -> 868960 | D78: =D66+D71-D77 -> 2889432 | E78: =E66+E71-E77 -> 4449920 | F78: =F66+F71-F77 -> 4793920
A79: Cumulative net impact | B79: =B78 -> -655512 | C79: =B79+C78 -> 213448 | D79: =C79+D78 -> 3102880 | E79: =D79+E78 -> 7552800 | F79: =E79+F78 -> 12346720
A80: Helper: year number if cumulative impact positive (else 99) | B80: =IF(B79>0,1,99) -> 99 | C80: =IF(C79>0,2,99) -> 2 | D80: =IF(D79>0,3,99) -> 3 | E80: =IF(E79>0,4,99) -> 4 | F80: =IF(F79>0,5,99) -> 5
